Metadata-Version: 2.1
Name: odoo14-addon-apps_download
Version: 14.0.1.0.1
Summary: Product Download for Appstore
Home-page: https://github.com/OCA/apps-store
Author: BizzAppDev, AgentERP, Elico Corp, Odoo Community Association (OCA)
Author-email: support@odoo-community.org
License: AGPL-3
Classifier: Programming Language :: Python
Classifier: Framework :: Odoo
Classifier: Framework :: Odoo :: 14.0
Classifier: License :: OSI Approved :: GNU Affero General Public License v3
Requires-Python: >=3.6
Requires-Dist: odoo14-addon-apps-product-creator
Requires-Dist: odoo14-addon-github-connector-odoo
Requires-Dist: odoo<14.1dev,>=14.0a
